[
  {
    "businessName": "Acme Financial 0",
    "positionName": "Director Consultant 0",
    "positionUrl": "https://example.com/job/0",
    "location": "USA",
    "seniority": "Junior",
    "uniqueKey": "Acme Financial 0-USA-Director Consultant 0-Junior-https://example.com/job/0"
  },
  {
    "businessName": "Acme Financial 1",
    "positionName": "Director Consultant 1",
    "positionUrl": "https://example.com/job/1",
    "location": "Japan",
    "seniority": "Mid",
    "uniqueKey": "Acme Financial 1-Japan-Director Consultant 1-Mid-https://example.com/job/1"
  },
  {
    "businessName": "Acme Financial 2",
    "positionName": "Director Consultant 2",
    "positionUrl": "https://example.com/job/2",
    "location": "Germany",
    "seniority": "Senior",
    "uniqueKey": "Acme Financial 2-Germany-Director Consultant 2-Senior-https://example.com/job/2"
  },
  {
    "businessName": "Acme Financial 3",
    "positionName": "Director Consultant 3",
    "positionUrl": "https://example.com/job/3",
    "location": "Brazil",
    "seniority": "Lead",
    "uniqueKey": "Acme Financial 3-Brazil-Director Consultant 3-Lead-https://example.com/job/3"
  },
  {
    "businessName": "Acme Financial 4",
    "positionName": "Director Consultant 4",
    "positionUrl": "https://example.com/job/4",
    "location": "India",
    "seniority": "VP",
    "uniqueKey": "Acme Financial 4-India-Director Consultant 4-VP-https://example.com/job/4"
  },
  {
    "businessName": "Acme Financial 5",
    "positionName": "Director Consultant 5",
    "positionUrl": "https://example.com/job/5",
    "location": "USA",
    "seniority": "Junior",
    "uniqueKey": "Acme Financial 5-USA-Director Consultant 5-Junior-https://example.com/job/5"
  },
  {
    "businessName": "Acme Financial 6",
    "positionName": "Director Consultant 6",
    "positionUrl": "https://example.com/job/6",
    "location": "Japan",
    "seniority": "Mid",
    "uniqueKey": "Acme Financial 6-Japan-Director Consultant 6-Mid-https://example.com/job/6"
  },
  {
    "businessName": "Acme Financial 7",
    "positionName": "Director Consultant 7",
    "positionUrl": "https://example.com/job/7",
    "location": "Germany",
    "seniority": "Senior",
    "uniqueKey": "Acme Financial 7-Germany-Director Consultant 7-Senior-https://example.com/job/7"
  },
  {
    "businessName": "Acme Financial 8",
    "positionName": "Director Consultant 8",
    "positionUrl": "https://example.com/job/8",
    "location": "Brazil",
    "seniority": "Lead",
    "uniqueKey": "Acme Financial 8-Brazil-Director Consultant 8-Lead-https://example.com/job/8"
  },
  {
    "businessName": "Acme Financial 9",
    "positionName": "Director Consultant 9",
    "positionUrl": "https://example.com/job/9",
    "location": "India",
    "seniority": "VP",
    "uniqueKey": "Acme Financial 9-India-Director Consultant 9-VP-https://example.com/job/9"
  },
  {
    "businessName": "Acme Financial 0",
    "positionName": "Director Consultant 10",
    "positionUrl": "https://example.com/job/10",
    "location": "USA",
    "seniority": "Junior",
    "uniqueKey": "Acme Financial 0-USA-Director Consultant 10-Junior-https://example.com/job/10"
  },
  {
    "businessName": "Acme Financial 1",
    "positionName": "Director Consultant 11",
    "positionUrl": "https://example.com/job/11",
    "location": "Japan",
    "seniority": "Mid",
    "uniqueKey": "Acme Financial 1-Japan-Director Consultant 11-Mid-https://example.com/job/11"
  },
  {
    "businessName": "Acme Financial 2",
    "positionName": "Director Consultant 12",
    "positionUrl": "https://example.com/job/12",
    "location": "Germany",
    "seniority": "Senior",
    "uniqueKey": "Acme Financial 2-Germany-Director Consultant 12-Senior-https://example.com/job/12"
  },
  {
    "businessName": "Acme Financial 3",
    "positionName": "Director Consultant 13",
    "positionUrl": "https://example.com/job/13",
    "location": "Brazil",
    "seniority": "Lead",
    "uniqueKey": "Acme Financial 3-Brazil-Director Consultant 13-Lead-https://example.com/job/13"
  },
  {
    "businessName": "Acme Financial 4",
    "positionName": "Director Consultant 14",
    "positionUrl": "https://example.com/job/14",
    "location": "India",
    "seniority": "VP",
    "uniqueKey": "Acme Financial 4-India-Director Consultant 14-VP-https://example.com/job/14"
  },
  {
    "businessName": "Acme Financial 5",
    "positionName": "Director Consultant 15",
    "positionUrl": "https://example.com/job/15",
    "location": "USA",
    "seniority": "Junior",
    "uniqueKey": "Acme Financial 5-USA-Director Consultant 15-Junior-https://example.com/job/15"
  },
  {
    "businessName": "Acme Financial 6",
    "positionName": "Director Consultant 16",
    "positionUrl": "https://example.com/job/16",
    "location": "Japan",
    "seniority": "Mid",
    "uniqueKey": "Acme Financial 6-Japan-Director Consultant 16-Mid-https://example.com/job/16"
  },
  {
    "businessName": "Acme Financial 7",
    "positionName": "Director Consultant 17",
    "positionUrl": "https://example.com/job/17",
    "location": "Germany",
    "seniority": "Senior",
    "uniqueKey": "Acme Financial 7-Germany-Director Consultant 17-Senior-https://example.com/job/17"
  },
  {
    "businessName": "Acme Financial 8",
    "positionName": "Director Consultant 18",
    "positionUrl": "https://example.com/job/18",
    "location": "Brazil",
    "seniority": "Lead",
    "uniqueKey": "Acme Financial 8-Brazil-Director Consultant 18-Lead-https://example.com/job/18"
  },
  {
    "businessName": "Acme Financial 9",
    "positionName": "Director Consultant 19",
    "positionUrl": "https://example.com/job/19",
    "location": "India",
    "seniority": "VP",
    "uniqueKey": "Acme Financial 9-India-Director Consultant 19-VP-https://example.com/job/19"
  },
  {
    "businessName": "Acme Financial 0",
    "positionName": "Director Consultant 20",
    "positionUrl": "https://example.com/job/20",
    "location": "USA",
    "seniority": "Junior",
    "uniqueKey": "Acme Financial 0-USA-Director Consultant 20-Junior-https://example.com/job/20"
  },
  {
    "businessName": "Acme Financial 1",
    "positionName": "Director Consultant 21",
    "positionUrl": "https://example.com/job/21",
    "location": "Japan",
    "seniority": "Mid",
    "uniqueKey": "Acme Financial 1-Japan-Director Consultant 21-Mid-https://example.com/job/21"
  },
  {
    "businessName": "Acme Financial 2",
    "positionName": "Director Consultant 22",
    "positionUrl": "https://example.com/job/22",
    "location": "Germany",
    "seniority": "Senior",
    "uniqueKey": "Acme Financial 2-Germany-Director Consultant 22-Senior-https://example.com/job/22"
  },
  {
    "businessName": "Acme Financial 3",
    "positionName": "Director Consultant 23",
    "positionUrl": "https://example.com/job/23",
    "location": "Brazil",
    "seniority": "Lead",
    "uniqueKey": "Acme Financial 3-Brazil-Director Consultant 23-Lead-https://example.com/job/23"
  },
  {
    "businessName": "Acme Financial 4",
    "positionName": "Director Consultant 24",
    "positionUrl": "https://example.com/job/24",
    "location": "India",
    "seniority": "VP",
    "uniqueKey": "Acme Financial 4-India-Director Consultant 24-VP-https://example.com/job/24"
  },
  {
    "businessName": "Acme Financial 5",
    "positionName": "Director Consultant 25",
    "positionUrl": "https://example.com/job/25",
    "location": "USA",
    "seniority": "Junior",
    "uniqueKey": "Acme Financial 5-USA-Director Consultant 25-Junior-https://example.com/job/25"
  },
  {
    "businessName": "Acme Financial 6",
    "positionName": "Director Consultant 26",
    "positionUrl": "https://example.com/job/26",
    "location": "Japan",
    "seniority": "Mid",
    "uniqueKey": "Acme Financial 6-Japan-Director Consultant 26-Mid-https://example.com/job/26"
  },
  {
    "businessName": "Acme Financial 7",
    "positionName": "Director Consultant 27",
    "positionUrl": "https://example.com/job/27",
    "location": "Germany",
    "seniority": "Senior",
    "uniqueKey": "Acme Financial 7-Germany-Director Consultant 27-Senior-https://example.com/job/27"
  },
  {
    "businessName": "Acme Financial 8",
    "positionName": "Director Consultant 28",
    "positionUrl": "https://example.com/job/28",
    "location": "Brazil",
    "seniority": "Lead",
    "uniqueKey": "Acme Financial 8-Brazil-Director Consultant 28-Lead-https://example.com/job/28"
  },
  {
    "businessName": "Acme Financial 9",
    "positionName": "Director Consultant 29",
    "positionUrl": "https://example.com/job/29",
    "location": "India",
    "seniority": "VP",
    "uniqueKey": "Acme Financial 9-India-Director Consultant 29-VP-https://example.com/job/29"
  },
  {
    "businessName": "Acme Financial 0",
    "positionName": "Director Consultant 30",
    "positionUrl": "https://example.com/job/30",
    "location": "USA",
    "seniority": "Junior",
    "uniqueKey": "Acme Financial 0-USA-Director Consultant 30-Junior-https://example.com/job/30"
  },
  {
    "businessName": "Acme Financial 1",
    "positionName": "Director Consultant 31",
    "positionUrl": "https://example.com/job/31",
    "location": "Japan",
    "seniority": "Mid",
    "uniqueKey": "Acme Financial 1-Japan-Director Consultant 31-Mid-https://example.com/job/31"
  },
  {
    "businessName": "Acme Financial 2",
    "positionName": "Director Consultant 32",
    "positionUrl": "https://example.com/job/32",
    "location": "Germany",
    "seniority": "Senior",
    "uniqueKey": "Acme Financial 2-Germany-Director Consultant 32-Senior-https://example.com/job/32"
  },
  {
    "businessName": "Acme Financial 3",
    "positionName": "Director Consultant 33",
    "positionUrl": "https://example.com/job/33",
    "location": "Brazil",
    "seniority": "Lead",
    "uniqueKey": "Acme Financial 3-Brazil-Director Consultant 33-Lead-https://example.com/job/33"
  },
  {
    "businessName": "Acme Financial 4",
    "positionName": "Director Consultant 34",
    "positionUrl": "https://example.com/job/34",
    "location": "India",
    "seniority": "VP",
    "uniqueKey": "Acme Financial 4-India-Director Consultant 34-VP-https://example.com/job/34"
  },
  {
    "businessName": "Acme Financial 5",
    "positionName": "Director Consultant 35",
    "positionUrl": "https://example.com/job/35",
    "location": "USA",
    "seniority": "Junior",
    "uniqueKey": "Acme Financial 5-USA-Director Consultant 35-Junior-https://example.com/job/35"
  },
  {
    "businessName": "Acme Financial 6",
    "positionName": "Director Consultant 36",
    "positionUrl": "https://example.com/job/36",
    "location": "Japan",
    "seniority": "Mid",
    "uniqueKey": "Acme Financial 6-Japan-Director Consultant 36-Mid-https://example.com/job/36"
  },
  {
    "businessName": "Acme Financial 7",
    "positionName": "Director Consultant 37",
    "positionUrl": "https://example.com/job/37",
    "location": "Germany",
    "seniority": "Senior",
    "uniqueKey": "Acme Financial 7-Germany-Director Consultant 37-Senior-https://example.com/job/37"
  },
  {
    "businessName": "Acme Financial 8",
    "positionName": "Director Consultant 38",
    "positionUrl": "https://example.com/job/38",
    "location": "Brazil",
    "seniority": "Lead",
    "uniqueKey": "Acme Financial 8-Brazil-Director Consultant 38-Lead-https://example.com/job/38"
  },
  {
    "businessName": "Acme Financial 9",
    "positionName": "Director Consultant 39",
    "positionUrl": "https://example.com/job/39",
    "location": "India",
    "seniority": "VP",
    "uniqueKey": "Acme Financial 9-India-Director Consultant 39-VP-https://example.com/job/39"
  },
  {
    "businessName": "Acme Financial 0",
    "positionName": "Director Consultant 40",
    "positionUrl": "https://example.com/job/40",
    "location": "USA",
    "seniority": "Junior",
    "uniqueKey": "Acme Financial 0-USA-Director Consultant 40-Junior-https://example.com/job/40"
  },
  {
    "businessName": "Acme Financial 1",
    "positionName": "Director Consultant 41",
    "positionUrl": "https://example.com/job/41",
    "location": "Japan",
    "seniority": "Mid",
    "uniqueKey": "Acme Financial 1-Japan-Director Consultant 41-Mid-https://example.com/job/41"
  },
  {
    "businessName": "Acme Financial 2",
    "positionName": "Director Consultant 42",
    "positionUrl": "https://example.com/job/42",
    "location": "Germany",
    "seniority": "Senior",
    "uniqueKey": "Acme Financial 2-Germany-Director Consultant 42-Senior-https://example.com/job/42"
  },
  {
    "businessName": "Acme Financial 3",
    "positionName": "Director Consultant 43",
    "positionUrl": "https://example.com/job/43",
    "location": "Brazil",
    "seniority": "Lead",
    "uniqueKey": "Acme Financial 3-Brazil-Director Consultant 43-Lead-https://example.com/job/43"
  },
  {
    "businessName": "Acme Financial 4",
    "positionName": "Director Consultant 44",
    "positionUrl": "https://example.com/job/44",
    "location": "India",
    "seniority": "VP",
    "uniqueKey": "Acme Financial 4-India-Director Consultant 44-VP-https://example.com/job/44"
  },
  {
    "businessName": "Acme Financial 5",
    "positionName": "Director Consultant 45",
    "positionUrl": "https://example.com/job/45",
    "location": "USA",
    "seniority": "Junior",
    "uniqueKey": "Acme Financial 5-USA-Director Consultant 45-Junior-https://example.com/job/45"
  },
  {
    "businessName": "Acme Financial 6",
    "positionName": "Director Consultant 46",
    "positionUrl": "https://example.com/job/46",
    "location": "Japan",
    "seniority": "Mid",
    "uniqueKey": "Acme Financial 6-Japan-Director Consultant 46-Mid-https://example.com/job/46"
  },
  {
    "businessName": "Acme Financial 7",
    "positionName": "Director Consultant 47",
    "positionUrl": "https://example.com/job/47",
    "location": "Germany",
    "seniority": "Senior",
    "uniqueKey": "Acme Financial 7-Germany-Director Consultant 47-Senior-https://example.com/job/47"
  },
  {
    "businessName": "Acme Financial 8",
    "positionName": "Director Consultant 48",
    "positionUrl": "https://example.com/job/48",
    "location": "Brazil",
    "seniority": "Lead",
    "uniqueKey": "Acme Financial 8-Brazil-Director Consultant 48-Lead-https://example.com/job/48"
  },
  {
    "businessName": "Acme Financial 9",
    "positionName": "Director Consultant 49",
    "positionUrl": "https://example.com/job/49",
    "location": "India",
    "seniority": "VP",
    "uniqueKey": "Acme Financial 9-India-Director Consultant 49-VP-https://example.com/job/49"
  },
  {
    "businessName": "Acme Financial 0",
    "positionName": "Director Consultant 50",
    "positionUrl": "https://example.com/job/50",
    "location": "USA",
    "seniority": "Junior",
    "uniqueKey": "Acme Financial 0-USA-Director Consultant 50-Junior-https://example.com/job/50"
  },
  {
    "businessName": "Acme Financial 1",
    "positionName": "Director Consultant 51",
    "positionUrl": "https://example.com/job/51",
    "location": "Japan",
    "seniority": "Mid",
    "uniqueKey": "Acme Financial 1-Japan-Director Consultant 51-Mid-https://example.com/job/51"
  },
  {
    "businessName": "Acme Financial 2",
    "positionName": "Director Consultant 52",
    "positionUrl": "https://example.com/job/52",
    "location": "Germany",
    "seniority": "Senior",
    "uniqueKey": "Acme Financial 2-Germany-Director Consultant 52-Senior-https://example.com/job/52"
  },
  {
    "businessName": "Acme Financial 3",
    "positionName": "Director Consultant 53",
    "positionUrl": "https://example.com/job/53",
    "location": "Brazil",
    "seniority": "Lead",
    "uniqueKey": "Acme Financial 3-Brazil-Director Consultant 53-Lead-https://example.com/job/53"
  },
  {
    "businessName": "Acme Financial 4",
    "positionName": "Director Consultant 54",
    "positionUrl": "https://example.com/job/54",
    "location": "India",
    "seniority": "VP",
    "uniqueKey": "Acme Financial 4-India-Director Consultant 54-VP-https://example.com/job/54"
  },
  {
    "businessName": "Acme Financial 5",
    "positionName": "Director Consultant 55",
    "positionUrl": "https://example.com/job/55",
    "location": "USA",
    "seniority": "Junior",
    "uniqueKey": "Acme Financial 5-USA-Director Consultant 55-Junior-https://example.com/job/55"
  },
  {
    "businessName": "Acme Financial 6",
    "positionName": "Director Consultant 56",
    "positionUrl": "https://example.com/job/56",
    "location": "Japan",
    "seniority": "Mid",
    "uniqueKey": "Acme Financial 6-Japan-Director Consultant 56-Mid-https://example.com/job/56"
  },
  {
    "businessName": "Acme Financial 7",
    "positionName": "Director Consultant 57",
    "positionUrl": "https://example.com/job/57",
    "location": "Germany",
    "seniority": "Senior",
    "uniqueKey": "Acme Financial 7-Germany-Director Consultant 57-Senior-https://example.com/job/57"
  },
  {
    "businessName": "Acme Financial 8",
    "positionName": "Director Consultant 58",
    "positionUrl": "https://example.com/job/58",
    "location": "Brazil",
    "seniority": "Lead",
    "uniqueKey": "Acme Financial 8-Brazil-Director Consultant 58-Lead-https://example.com/job/58"
  },
  {
    "businessName": "Acme Financial 9",
    "positionName": "Director Consultant 59",
    "positionUrl": "https://example.com/job/59",
    "location": "India",
    "seniority": "VP",
    "uniqueKey": "Acme Financial 9-India-Director Consultant 59-VP-https://example.com/job/59"
  },
  {
    "businessName": "Acme Financial 0",
    "positionName": "Director Consultant 60",
    "positionUrl": "https://example.com/job/60",
    "location": "USA",
    "seniority": "Junior",
    "uniqueKey": "Acme Financial 0-USA-Director Consultant 60-Junior-https://example.com/job/60"
  },
  {
    "businessName": "Acme Financial 1",
    "positionName": "Director Consultant 61",
    "positionUrl": "https://example.com/job/61",
    "location": "Japan",
    "seniority": "Mid",
    "uniqueKey": "Acme Financial 1-Japan-Director Consultant 61-Mid-https://example.com/job/61"
  },
  {
    "businessName": "Acme Financial 2",
    "positionName": "Director Consultant 62",
    "positionUrl": "https://example.com/job/62",
    "location": "Germany",
    "seniority": "Senior",
    "uniqueKey": "Acme Financial 2-Germany-Director Consultant 62-Senior-https://example.com/job/62"
  },
  {
    "businessName": "Acme Financial 3",
    "positionName": "Director Consultant 63",
    "positionUrl": "https://example.com/job/63",
    "location": "Brazil",
    "seniority": "Lead",
    "uniqueKey": "Acme Financial 3-Brazil-Director Consultant 63-Lead-https://example.com/job/63"
  },
  {
    "businessName": "Acme Financial 4",
    "positionName": "Director Consultant 64",
    "positionUrl": "https://example.com/job/64",
    "location": "India",
    "seniority": "VP",
    "uniqueKey": "Acme Financial 4-India-Director Consultant 64-VP-https://example.com/job/64"
  },
  {
    "businessName": "Acme Financial 5",
    "positionName": "Director Consultant 65",
    "positionUrl": "https://example.com/job/65",
    "location": "USA",
    "seniority": "Junior",
    "uniqueKey": "Acme Financial 5-USA-Director Consultant 65-Junior-https://example.com/job/65"
  },
  {
    "businessName": "Acme Financial 6",
    "positionName": "Director Consultant 66",
    "positionUrl": "https://example.com/job/66",
    "location": "Japan",
    "seniority": "Mid",
    "uniqueKey": "Acme Financial 6-Japan-Director Consultant 66-Mid-https://example.com/job/66"
  },
  {
    "businessName": "Acme Financial 7",
    "positionName": "Director Consultant 67",
    "positionUrl": "https://example.com/job/67",
    "location": "Germany",
    "seniority": "Senior",
    "uniqueKey": "Acme Financial 7-Germany-Director Consultant 67-Senior-https://example.com/job/67"
  },
  {
    "businessName": "Acme Financial 8",
    "positionName": "Director Consultant 68",
    "positionUrl": "https://example.com/job/68",
    "location": "Brazil",
    "seniority": "Lead",
    "uniqueKey": "Acme Financial 8-Brazil-Director Consultant 68-Lead-https://example.com/job/68"
  },
  {
    "businessName": "Acme Financial 9",
    "positionName": "Director Consultant 69",
    "positionUrl": "https://example.com/job/69",
    "location": "India",
    "seniority": "VP",
    "uniqueKey": "Acme Financial 9-India-Director Consultant 69-VP-https://example.com/job/69"
  },
  {
    "businessName": "Acme Financial 0",
    "positionName": "Director Consultant 70",
    "positionUrl": "https://example.com/job/70",
    "location": "USA",
    "seniority": "Junior",
    "uniqueKey": "Acme Financial 0-USA-Director Consultant 70-Junior-https://example.com/job/70"
  },
  {
    "businessName": "Acme Financial 1",
    "positionName": "Director Consultant 71",
    "positionUrl": "https://example.com/job/71",
    "location": "Japan",
    "seniority": "Mid",
    "uniqueKey": "Acme Financial 1-Japan-Director Consultant 71-Mid-https://example.com/job/71"
  },
  {
    "businessName": "Acme Financial 2",
    "positionName": "Director Consultant 72",
    "positionUrl": "https://example.com/job/72",
    "location": "Germany",
    "seniority": "Senior",
    "uniqueKey": "Acme Financial 2-Germany-Director Consultant 72-Senior-https://example.com/job/72"
  },
  {
    "businessName": "Acme Financial 3",
    "positionName": "Director Consultant 73",
    "positionUrl": "https://example.com/job/73",
    "location": "Brazil",
    "seniority": "Lead",
    "uniqueKey": "Acme Financial 3-Brazil-Director Consultant 73-Lead-https://example.com/job/73"
  },
  {
    "businessName": "Acme Financial 4",
    "positionName": "Director Consultant 74",
    "positionUrl": "https://example.com/job/74",
    "location": "India",
    "seniority": "VP",
    "uniqueKey": "Acme Financial 4-India-Director Consultant 74-VP-https://example.com/job/74"
  },
  {
    "businessName": "Acme Financial 5",
    "positionName": "Director Consultant 75",
    "positionUrl": "https://example.com/job/75",
    "location": "USA",
    "seniority": "Junior",
    "uniqueKey": "Acme Financial 5-USA-Director Consultant 75-Junior-https://example.com/job/75"
  },
  {
    "businessName": "Acme Financial 6",
    "positionName": "Director Consultant 76",
    "positionUrl": "https://example.com/job/76",
    "location": "Japan",
    "seniority": "Mid",
    "uniqueKey": "Acme Financial 6-Japan-Director Consultant 76-Mid-https://example.com/job/76"
  },
  {
    "businessName": "Acme Financial 7",
    "positionName": "Director Consultant 77",
    "positionUrl": "https://example.com/job/77",
    "location": "Germany",
    "seniority": "Senior",
    "uniqueKey": "Acme Financial 7-Germany-Director Consultant 77-Senior-https://example.com/job/77"
  },
  {
    "businessName": "Acme Financial 8",
    "positionName": "Director Consultant 78",
    "positionUrl": "https://example.com/job/78",
    "location": "Brazil",
    "seniority": "Lead",
    "uniqueKey": "Acme Financial 8-Brazil-Director Consultant 78-Lead-https://example.com/job/78"
  },
  {
    "businessName": "Acme Financial 9",
    "positionName": "Director Consultant 79",
    "positionUrl": "https://example.com/job/79",
    "location": "India",
    "seniority": "VP",
    "uniqueKey": "Acme Financial 9-India-Director Consultant 79-VP-https://example.com/job/79"
  },
  {
    "businessName": "Acme Financial 0",
    "positionName": "Director Consultant 80",
    "positionUrl": "https://example.com/job/80",
    "location": "USA",
    "seniority": "Junior",
    "uniqueKey": "Acme Financial 0-USA-Director Consultant 80-Junior-https://example.com/job/80"
  },
  {
    "businessName": "Acme Financial 1",
    "positionName": "Director Consultant 81",
    "positionUrl": "https://example.com/job/81",
    "location": "Japan",
    "seniority": "Mid",
    "uniqueKey": "Acme Financial 1-Japan-Director Consultant 81-Mid-https://example.com/job/81"
  },
  {
    "businessName": "Acme Financial 2",
    "positionName": "Director Consultant 82",
    "positionUrl": "https://example.com/job/82",
    "location": "Germany",
    "seniority": "Senior",
    "uniqueKey": "Acme Financial 2-Germany-Director Consultant 82-Senior-https://example.com/job/82"
  },
  {
    "businessName": "Acme Financial 3",
    "positionName": "Director Consultant 83",
    "positionUrl": "https://example.com/job/83",
    "location": "Brazil",
    "seniority": "Lead",
    "uniqueKey": "Acme Financial 3-Brazil-Director Consultant 83-Lead-https://example.com/job/83"
  },
  {
    "businessName": "Acme Financial 4",
    "positionName": "Director Consultant 84",
    "positionUrl": "https://example.com/job/84",
    "location": "India",
    "seniority": "VP",
    "uniqueKey": "Acme Financial 4-India-Director Consultant 84-VP-https://example.com/job/84"
  },
  {
    "businessName": "Acme Financial 5",
    "positionName": "Director Consultant 85",
    "positionUrl": "https://example.com/job/85",
    "location": "USA",
    "seniority": "Junior",
    "uniqueKey": "Acme Financial 5-USA-Director Consultant 85-Junior-https://example.com/job/85"
  },
  {
    "businessName": "Acme Financial 6",
    "positionName": "Director Consultant 86",
    "positionUrl": "https://example.com/job/86",
    "location": "Japan",
    "seniority": "Mid",
    "uniqueKey": "Acme Financial 6-Japan-Director Consultant 86-Mid-https://example.com/job/86"
  },
  {
    "businessName": "Acme Financial 7",
    "positionName": "Director Consultant 87",
    "positionUrl": "https://example.com/job/87",
    "location": "Germany",
    "seniority": "Senior",
    "uniqueKey": "Acme Financial 7-Germany-Director Consultant 87-Senior-https://example.com/job/87"
  },
  {
    "businessName": "Acme Financial 8",
    "positionName": "Director Consultant 88",
    "positionUrl": "https://example.com/job/88",
    "location": "Brazil",
    "seniority": "Lead",
    "uniqueKey": "Acme Financial 8-Brazil-Director Consultant 88-Lead-https://example.com/job/88"
  },
  {
    "businessName": "Acme Financial 9",
    "positionName": "Director Consultant 89",
    "positionUrl": "https://example.com/job/89",
    "location": "India",
    "seniority": "VP",
    "uniqueKey": "Acme Financial 9-India-Director Consultant 89-VP-https://example.com/job/89"
  },
  {
    "businessName": "Acme Financial 0",
    "positionName": "Director Consultant 90",
    "positionUrl": "https://example.com/job/90",
    "location": "USA",
    "seniority": "Junior",
    "uniqueKey": "Acme Financial 0-USA-Director Consultant 90-Junior-https://example.com/job/90"
  },
  {
    "businessName": "Acme Financial 1",
    "positionName": "Director Consultant 91",
    "positionUrl": "https://example.com/job/91",
    "location": "Japan",
    "seniority": "Mid",
    "uniqueKey": "Acme Financial 1-Japan-Director Consultant 91-Mid-https://example.com/job/91"
  },
  {
    "businessName": "Acme Financial 2",
    "positionName": "Director Consultant 92",
    "positionUrl": "https://example.com/job/92",
    "location": "Germany",
    "seniority": "Senior",
    "uniqueKey": "Acme Financial 2-Germany-Director Consultant 92-Senior-https://example.com/job/92"
  },
  {
    "businessName": "Acme Financial 3",
    "positionName": "Director Consultant 93",
    "positionUrl": "https://example.com/job/93",
    "location": "Brazil",
    "seniority": "Lead",
    "uniqueKey": "Acme Financial 3-Brazil-Director Consultant 93-Lead-https://example.com/job/93"
  },
  {
    "businessName": "Acme Financial 4",
    "positionName": "Director Consultant 94",
    "positionUrl": "https://example.com/job/94",
    "location": "India",
    "seniority": "VP",
    "uniqueKey": "Acme Financial 4-India-Director Consultant 94-VP-https://example.com/job/94"
  },
  {
    "businessName": "Acme Financial 5",
    "positionName": "Director Consultant 95",
    "positionUrl": "https://example.com/job/95",
    "location": "USA",
    "seniority": "Junior",
    "uniqueKey": "Acme Financial 5-USA-Director Consultant 95-Junior-https://example.com/job/95"
  },
  {
    "businessName": "Acme Financial 6",
    "positionName": "Director Consultant 96",
    "positionUrl": "https://example.com/job/96",
    "location": "Japan",
    "seniority": "Mid",
    "uniqueKey": "Acme Financial 6-Japan-Director Consultant 96-Mid-https://example.com/job/96"
  },
  {
    "businessName": "Acme Financial 7",
    "positionName": "Director Consultant 97",
    "positionUrl": "https://example.com/job/97",
    "location": "Germany",
    "seniority": "Senior",
    "uniqueKey": "Acme Financial 7-Germany-Director Consultant 97-Senior-https://example.com/job/97"
  },
  {
    "businessName": "Acme Financial 8",
    "positionName": "Director Consultant 98",
    "positionUrl": "https://example.com/job/98",
    "location": "Brazil",
    "seniority": "Lead",
    "uniqueKey": "Acme Financial 8-Brazil-Director Consultant 98-Lead-https://example.com/job/98"
  },
  {
    "businessName": "Acme Financial 9",
    "positionName": "Director Consultant 99",
    "positionUrl": "https://example.com/job/99",
    "location": "India",
    "seniority": "VP",
    "uniqueKey": "Acme Financial 9-India-Director Consultant 99-VP-https://example.com/job/99"
  },
  {
    "businessName": "Acme Financial 0",
    "positionName": "Director Consultant 100",
    "positionUrl": "https://example.com/job/100",
    "location": "USA",
    "seniority": "Junior",
    "uniqueKey": "Acme Financial 0-USA-Director Consultant 100-Junior-https://example.com/job/100"
  },
  {
    "businessName": "Acme Financial 1",
    "positionName": "Director Consultant 101",
    "positionUrl": "https://example.com/job/101",
    "location": "Japan",
    "seniority": "Mid",
    "uniqueKey": "Acme Financial 1-Japan-Director Consultant 101-Mid-https://example.com/job/101"
  },
  {
    "businessName": "Acme Financial 2",
    "positionName": "Director Consultant 102",
    "positionUrl": "https://example.com/job/102",
    "location": "Germany",
    "seniority": "Senior",
    "uniqueKey": "Acme Financial 2-Germany-Director Consultant 102-Senior-https://example.com/job/102"
  },
  {
    "businessName": "Acme Financial 3",
    "positionName": "Director Consultant 103",
    "positionUrl": "https://example.com/job/103",
    "location": "Brazil",
    "seniority": "Lead",
    "uniqueKey": "Acme Financial 3-Brazil-Director Consultant 103-Lead-https://example.com/job/103"
  },
  {
    "businessName": "Acme Financial 4",
    "positionName": "Director Consultant 104",
    "positionUrl": "https://example.com/job/104",
    "location": "India",
    "seniority": "VP",
    "uniqueKey": "Acme Financial 4-India-Director Consultant 104-VP-https://example.com/job/104"
  },
  {
    "businessName": "Acme Financial 5",
    "positionName": "Director Consultant 105",
    "positionUrl": "https://example.com/job/105",
    "location": "USA",
    "seniority": "Junior",
    "uniqueKey": "Acme Financial 5-USA-Director Consultant 105-Junior-https://example.com/job/105"
  },
  {
    "businessName": "Acme Financial 6",
    "positionName": "Director Consultant 106",
    "positionUrl": "https://example.com/job/106",
    "location": "Japan",
    "seniority": "Mid",
    "uniqueKey": "Acme Financial 6-Japan-Director Consultant 106-Mid-https://example.com/job/106"
  },
  {
    "businessName": "Acme Financial 7",
    "positionName": "Director Consultant 107",
    "positionUrl": "https://example.com/job/107",
    "location": "Germany",
    "seniority": "Senior",
    "uniqueKey": "Acme Financial 7-Germany-Director Consultant 107-Senior-https://example.com/job/107"
  },
  {
    "businessName": "Acme Financial 8",
    "positionName": "Director Consultant 108",
    "positionUrl": "https://example.com/job/108",
    "location": "Brazil",
    "seniority": "Lead",
    "uniqueKey": "Acme Financial 8-Brazil-Director Consultant 108-Lead-https://example.com/job/108"
  },
  {
    "businessName": "Acme Financial 9",
    "positionName": "Director Consultant 109",
    "positionUrl": "https://example.com/job/109",
    "location": "India",
    "seniority": "VP",
    "uniqueKey": "Acme Financial 9-India-Director Consultant 109-VP-https://example.com/job/109"
  },
  {
    "businessName": "Acme Financial 0",
    "positionName": "Director Consultant 110",
    "positionUrl": "https://example.com/job/110",
    "location": "USA",
    "seniority": "Junior",
    "uniqueKey": "Acme Financial 0-USA-Director Consultant 110-Junior-https://example.com/job/110"
  },
  {
    "businessName": "Acme Financial 1",
    "positionName": "Director Consultant 111",
    "positionUrl": "https://example.com/job/111",
    "location": "Japan",
    "seniority": "Mid",
    "uniqueKey": "Acme Financial 1-Japan-Director Consultant 111-Mid-https://example.com/job/111"
  },
  {
    "businessName": "Acme Financial 2",
    "positionName": "Director Consultant 112",
    "positionUrl": "https://example.com/job/112",
    "location": "Germany",
    "seniority": "Senior",
    "uniqueKey": "Acme Financial 2-Germany-Director Consultant 112-Senior-https://example.com/job/112"
  },
  {
    "businessName": "Acme Financial 3",
    "positionName": "Director Consultant 113",
    "positionUrl": "https://example.com/job/113",
    "location": "Brazil",
    "seniority": "Lead",
    "uniqueKey": "Acme Financial 3-Brazil-Director Consultant 113-Lead-https://example.com/job/113"
  },
  {
    "businessName": "Acme Financial 4",
    "positionName": "Director Consultant 114",
    "positionUrl": "https://example.com/job/114",
    "location": "India",
    "seniority": "VP",
    "uniqueKey": "Acme Financial 4-India-Director Consultant 114-VP-https://example.com/job/114"
  },
  {
    "businessName": "Acme Financial 5",
    "positionName": "Director Consultant 115",
    "positionUrl": "https://example.com/job/115",
    "location": "USA",
    "seniority": "Junior",
    "uniqueKey": "Acme Financial 5-USA-Director Consultant 115-Junior-https://example.com/job/115"
  },
  {
    "businessName": "Acme Financial 6",
    "positionName": "Director Consultant 116",
    "positionUrl": "https://example.com/job/116",
    "location": "Japan",
    "seniority": "Mid",
    "uniqueKey": "Acme Financial 6-Japan-Director Consultant 116-Mid-https://example.com/job/116"
  },
  {
    "businessName": "Acme Financial 7",
    "positionName": "Director Consultant 117",
    "positionUrl": "https://example.com/job/117",
    "location": "Germany",
    "seniority": "Senior",
    "uniqueKey": "Acme Financial 7-Germany-Director Consultant 117-Senior-https://example.com/job/117"
  },
  {
    "businessName": "Acme Financial 8",
    "positionName": "Director Consultant 118",
    "positionUrl": "https://example.com/job/118",
    "location": "Brazil",
    "seniority": "Lead",
    "uniqueKey": "Acme Financial 8-Brazil-Director Consultant 118-Lead-https://example.com/job/118"
  },
  {
    "businessName": "Acme Financial 9",
    "positionName": "Director Consultant 119",
    "positionUrl": "https://example.com/job/119",
    "location": "India",
    "seniority": "VP",
    "uniqueKey": "Acme Financial 9-India-Director Consultant 119-VP-https://example.com/job/119"
  },
  {
    "businessName": "Acme Financial 0",
    "positionName": "Director Consultant 120",
    "positionUrl": "https://example.com/job/120",
    "location": "USA",
    "seniority": "Junior",
    "uniqueKey": "Acme Financial 0-USA-Director Consultant 120-Junior-https://example.com/job/120"
  },
  {
    "businessName": "Acme Financial 1",
    "positionName": "Director Consultant 121",
    "positionUrl": "https://example.com/job/121",
    "location": "Japan",
    "seniority": "Mid",
    "uniqueKey": "Acme Financial 1-Japan-Director Consultant 121-Mid-https://example.com/job/121"
  },
  {
    "businessName": "Acme Financial 2",
    "positionName": "Director Consultant 122",
    "positionUrl": "https://example.com/job/122",
    "location": "Germany",
    "seniority": "Senior",
    "uniqueKey": "Acme Financial 2-Germany-Director Consultant 122-Senior-https://example.com/job/122"
  },
  {
    "businessName": "Acme Financial 3",
    "positionName": "Director Consultant 123",
    "positionUrl": "https://example.com/job/123",
    "location": "Brazil",
    "seniority": "Lead",
    "uniqueKey": "Acme Financial 3-Brazil-Director Consultant 123-Lead-https://example.com/job/123"
  },
  {
    "businessName": "Acme Financial 4",
    "positionName": "Director Consultant 124",
    "positionUrl": "https://example.com/job/124",
    "location": "India",
    "seniority": "VP",
    "uniqueKey": "Acme Financial 4-India-Director Consultant 124-VP-https://example.com/job/124"
  },
  {
    "businessName": "Acme Financial 5",
    "positionName": "Director Consultant 125",
    "positionUrl": "https://example.com/job/125",
    "location": "USA",
    "seniority": "Junior",
    "uniqueKey": "Acme Financial 5-USA-Director Consultant 125-Junior-https://example.com/job/125"
  },
  {
    "businessName": "Acme Financial 6",
    "positionName": "Director Consultant 126",
    "positionUrl": "https://example.com/job/126",
    "location": "Japan",
    "seniority": "Mid",
    "uniqueKey": "Acme Financial 6-Japan-Director Consultant 126-Mid-https://example.com/job/126"
  },
  {
    "businessName": "Acme Financial 7",
    "positionName": "Director Consultant 127",
    "positionUrl": "https://example.com/job/127",
    "location": "Germany",
    "seniority": "Senior",
    "uniqueKey": "Acme Financial 7-Germany-Director Consultant 127-Senior-https://example.com/job/127"
  },
  {
    "businessName": "Acme Financial 8",
    "positionName": "Director Consultant 128",
    "positionUrl": "https://example.com/job/128",
    "location": "Brazil",
    "seniority": "Lead",
    "uniqueKey": "Acme Financial 8-Brazil-Director Consultant 128-Lead-https://example.com/job/128"
  },
  {
    "businessName": "Acme Financial 9",
    "positionName": "Director Consultant 129",
    "positionUrl": "https://example.com/job/129",
    "location": "India",
    "seniority": "VP",
    "uniqueKey": "Acme Financial 9-India-Director Consultant 129-VP-https://example.com/job/129"
  },
  {
    "businessName": "Acme Financial 0",
    "positionName": "Director Consultant 130",
    "positionUrl": "https://example.com/job/130",
    "location": "USA",
    "seniority": "Junior",
    "uniqueKey": "Acme Financial 0-USA-Director Consultant 130-Junior-https://example.com/job/130"
  },
  {
    "businessName": "Acme Financial 1",
    "positionName": "Director Consultant 131",
    "positionUrl": "https://example.com/job/131",
    "location": "Japan",
    "seniority": "Mid",
    "uniqueKey": "Acme Financial 1-Japan-Director Consultant 131-Mid-https://example.com/job/131"
  },
  {
    "businessName": "Acme Financial 2",
    "positionName": "Director Consultant 132",
    "positionUrl": "https://example.com/job/132",
    "location": "Germany",
    "seniority": "Senior",
    "uniqueKey": "Acme Financial 2-Germany-Director Consultant 132-Senior-https://example.com/job/132"
  },
  {
    "businessName": "Acme Financial 3",
    "positionName": "Director Consultant 133",
    "positionUrl": "https://example.com/job/133",
    "location": "Brazil",
    "seniority": "Lead",
    "uniqueKey": "Acme Financial 3-Brazil-Director Consultant 133-Lead-https://example.com/job/133"
  },
  {
    "businessName": "Acme Financial 4",
    "positionName": "Director Consultant 134",
    "positionUrl": "https://example.com/job/134",
    "location": "India",
    "seniority": "VP",
    "uniqueKey": "Acme Financial 4-India-Director Consultant 134-VP-https://example.com/job/134"
  },
  {
    "businessName": "Acme Financial 5",
    "positionName": "Director Consultant 135",
    "positionUrl": "https://example.com/job/135",
    "location": "USA",
    "seniority": "Junior",
    "uniqueKey": "Acme Financial 5-USA-Director Consultant 135-Junior-https://example.com/job/135"
  },
  {
    "businessName": "Acme Financial 6",
    "positionName": "Director Consultant 136",
    "positionUrl": "https://example.com/job/136",
    "location": "Japan",
    "seniority": "Mid",
    "uniqueKey": "Acme Financial 6-Japan-Director Consultant 136-Mid-https://example.com/job/136"
  },
  {
    "businessName": "Acme Financial 7",
    "positionName": "Director Consultant 137",
    "positionUrl": "https://example.com/job/137",
    "location": "Germany",
    "seniority": "Senior",
    "uniqueKey": "Acme Financial 7-Germany-Director Consultant 137-Senior-https://example.com/job/137"
  },
  {
    "businessName": "Acme Financial 8",
    "positionName": "Director Consultant 138",
    "positionUrl": "https://example.com/job/138",
    "location": "Brazil",
    "seniority": "Lead",
    "uniqueKey": "Acme Financial 8-Brazil-Director Consultant 138-Lead-https://example.com/job/138"
  },
  {
    "businessName": "Acme Financial 9",
    "positionName": "Director Consultant 139",
    "positionUrl": "https://example.com/job/139",
    "location": "India",
    "seniority": "VP",
    "uniqueKey": "Acme Financial 9-India-Director Consultant 139-VP-https://example.com/job/139"
  },
  {
    "businessName": "Acme Financial 0",
    "positionName": "Director Consultant 140",
    "positionUrl": "https://example.com/job/140",
    "location": "USA",
    "seniority": "Junior",
    "uniqueKey": "Acme Financial 0-USA-Director Consultant 140-Junior-https://example.com/job/140"
  },
  {
    "businessName": "Acme Financial 1",
    "positionName": "Director Consultant 141",
    "positionUrl": "https://example.com/job/141",
    "location": "Japan",
    "seniority": "Mid",
    "uniqueKey": "Acme Financial 1-Japan-Director Consultant 141-Mid-https://example.com/job/141"
  },
  {
    "businessName": "Acme Financial 2",
    "positionName": "Director Consultant 142",
    "positionUrl": "https://example.com/job/142",
    "location": "Germany",
    "seniority": "Senior",
    "uniqueKey": "Acme Financial 2-Germany-Director Consultant 142-Senior-https://example.com/job/142"
  },
  {
    "businessName": "Acme Financial 3",
    "positionName": "Director Consultant 143",
    "positionUrl": "https://example.com/job/143",
    "location": "Brazil",
    "seniority": "Lead",
    "uniqueKey": "Acme Financial 3-Brazil-Director Consultant 143-Lead-https://example.com/job/143"
  },
  {
    "businessName": "Acme Financial 4",
    "positionName": "Director Consultant 144",
    "positionUrl": "https://example.com/job/144",
    "location": "India",
    "seniority": "VP",
    "uniqueKey": "Acme Financial 4-India-Director Consultant 144-VP-https://example.com/job/144"
  },
  {
    "businessName": "Acme Financial 5",
    "positionName": "Director Consultant 145",
    "positionUrl": "https://example.com/job/145",
    "location": "USA",
    "seniority": "Junior",
    "uniqueKey": "Acme Financial 5-USA-Director Consultant 145-Junior-https://example.com/job/145"
  },
  {
    "businessName": "Acme Financial 6",
    "positionName": "Director Consultant 146",
    "positionUrl": "https://example.com/job/146",
    "location": "Japan",
    "seniority": "Mid",
    "uniqueKey": "Acme Financial 6-Japan-Director Consultant 146-Mid-https://example.com/job/146"
  },
  {
    "businessName": "Acme Financial 7",
    "positionName": "Director Consultant 147",
    "positionUrl": "https://example.com/job/147",
    "location": "Germany",
    "seniority": "Senior",
    "uniqueKey": "Acme Financial 7-Germany-Director Consultant 147-Senior-https://example.com/job/147"
  },
  {
    "businessName": "Acme Financial 8",
    "positionName": "Director Consultant 148",
    "positionUrl": "https://example.com/job/148",
    "location": "Brazil",
    "seniority": "Lead",
    "uniqueKey": "Acme Financial 8-Brazil-Director Consultant 148-Lead-https://example.com/job/148"
  },
  {
    "businessName": "Acme Financial 9",
    "positionName": "Director Consultant 149",
    "positionUrl": "https://example.com/job/149",
    "location": "India",
    "seniority": "VP",
    "uniqueKey": "Acme Financial 9-India-Director Consultant 149-VP-https://example.com/job/149"
  },
  {
    "businessName": "Acme Financial 0",
    "positionName": "Director Consultant 150",
    "positionUrl": "https://example.com/job/150",
    "location": "USA",
    "seniority": "Junior",
    "uniqueKey": "Acme Financial 0-USA-Director Consultant 150-Junior-https://example.com/job/150"
  },
  {
    "businessName": "Acme Financial 1",
    "positionName": "Director Consultant 151",
    "positionUrl": "https://example.com/job/151",
    "location": "Japan",
    "seniority": "Mid",
    "uniqueKey": "Acme Financial 1-Japan-Director Consultant 151-Mid-https://example.com/job/151"
  },
  {
    "businessName": "Acme Financial 2",
    "positionName": "Director Consultant 152",
    "positionUrl": "https://example.com/job/152",
    "location": "Germany",
    "seniority": "Senior",
    "uniqueKey": "Acme Financial 2-Germany-Director Consultant 152-Senior-https://example.com/job/152"
  },
  {
    "businessName": "Acme Financial 3",
    "positionName": "Director Consultant 153",
    "positionUrl": "https://example.com/job/153",
    "location": "Brazil",
    "seniority": "Lead",
    "uniqueKey": "Acme Financial 3-Brazil-Director Consultant 153-Lead-https://example.com/job/153"
  },
  {
    "businessName": "Acme Financial 4",
    "positionName": "Director Consultant 154",
    "positionUrl": "https://example.com/job/154",
    "location": "India",
    "seniority": "VP",
    "uniqueKey": "Acme Financial 4-India-Director Consultant 154-VP-https://example.com/job/154"
  },
  {
    "businessName": "Acme Financial 5",
    "positionName": "Director Consultant 155",
    "positionUrl": "https://example.com/job/155",
    "location": "USA",
    "seniority": "Junior",
    "uniqueKey": "Acme Financial 5-USA-Director Consultant 155-Junior-https://example.com/job/155"
  },
  {
    "businessName": "Acme Financial 6",
    "positionName": "Director Consultant 156",
    "positionUrl": "https://example.com/job/156",
    "location": "Japan",
    "seniority": "Mid",
    "uniqueKey": "Acme Financial 6-Japan-Director Consultant 156-Mid-https://example.com/job/156"
  },
  {
    "businessName": "Acme Financial 7",
    "positionName": "Director Consultant 157",
    "positionUrl": "https://example.com/job/157",
    "location": "Germany",
    "seniority": "Senior",
    "uniqueKey": "Acme Financial 7-Germany-Director Consultant 157-Senior-https://example.com/job/157"
  },
  {
    "businessName": "Acme Financial 8",
    "positionName": "Director Consultant 158",
    "positionUrl": "https://example.com/job/158",
    "location": "Brazil",
    "seniority": "Lead",
    "uniqueKey": "Acme Financial 8-Brazil-Director Consultant 158-Lead-https://example.com/job/158"
  },
  {
    "businessName": "Acme Financial 9",
    "positionName": "Director Consultant 159",
    "positionUrl": "https://example.com/job/159",
    "location": "India",
    "seniority": "VP",
    "uniqueKey": "Acme Financial 9-India-Director Consultant 159-VP-https://example.com/job/159"
  },
  {
    "businessName": "Acme Financial 0",
    "positionName": "Director Consultant 160",
    "positionUrl": "https://example.com/job/160",
    "location": "USA",
    "seniority": "Junior",
    "uniqueKey": "Acme Financial 0-USA-Director Consultant 160-Junior-https://example.com/job/160"
  },
  {
    "businessName": "Acme Financial 1",
    "positionName": "Director Consultant 161",
    "positionUrl": "https://example.com/job/161",
    "location": "Japan",
    "seniority": "Mid",
    "uniqueKey": "Acme Financial 1-Japan-Director Consultant 161-Mid-https://example.com/job/161"
  },
  {
    "businessName": "Acme Financial 2",
    "positionName": "Director Consultant 162",
    "positionUrl": "https://example.com/job/162",
    "location": "Germany",
    "seniority": "Senior",
    "uniqueKey": "Acme Financial 2-Germany-Director Consultant 162-Senior-https://example.com/job/162"
  },
  {
    "businessName": "Acme Financial 3",
    "positionName": "Director Consultant 163",
    "positionUrl": "https://example.com/job/163",
    "location": "Brazil",
    "seniority": "Lead",
    "uniqueKey": "Acme Financial 3-Brazil-Director Consultant 163-Lead-https://example.com/job/163"
  },
  {
    "businessName": "Acme Financial 4",
    "positionName": "Director Consultant 164",
    "positionUrl": "https://example.com/job/164",
    "location": "India",
    "seniority": "VP",
    "uniqueKey": "Acme Financial 4-India-Director Consultant 164-VP-https://example.com/job/164"
  },
  {
    "businessName": "Acme Financial 5",
    "positionName": "Director Consultant 165",
    "positionUrl": "https://example.com/job/165",
    "location": "USA",
    "seniority": "Junior",
    "uniqueKey": "Acme Financial 5-USA-Director Consultant 165-Junior-https://example.com/job/165"
  },
  {
    "businessName": "Acme Financial 6",
    "positionName": "Director Consultant 166",
    "positionUrl": "https://example.com/job/166",
    "location": "Japan",
    "seniority": "Mid",
    "uniqueKey": "Acme Financial 6-Japan-Director Consultant 166-Mid-https://example.com/job/166"
  },
  {
    "businessName": "Acme Financial 7",
    "positionName": "Director Consultant 167",
    "positionUrl": "https://example.com/job/167",
    "location": "Germany",
    "seniority": "Senior",
    "uniqueKey": "Acme Financial 7-Germany-Director Consultant 167-Senior-https://example.com/job/167"
  },
  {
    "businessName": "Acme Financial 8",
    "positionName": "Director Consultant 168",
    "positionUrl": "https://example.com/job/168",
    "location": "Brazil",
    "seniority": "Lead",
    "uniqueKey": "Acme Financial 8-Brazil-Director Consultant 168-Lead-https://example.com/job/168"
  },
  {
    "businessName": "Acme Financial 9",
    "positionName": "Director Consultant 169",
    "positionUrl": "https://example.com/job/169",
    "location": "India",
    "seniority": "VP",
    "uniqueKey": "Acme Financial 9-India-Director Consultant 169-VP-https://example.com/job/169"
  },
  {
    "businessName": "Acme Financial 0",
    "positionName": "Director Consultant 170",
    "positionUrl": "https://example.com/job/170",
    "location": "USA",
    "seniority": "Junior",
    "uniqueKey": "Acme Financial 0-USA-Director Consultant 170-Junior-https://example.com/job/170"
  },
  {
    "businessName": "Acme Financial 1",
    "positionName": "Director Consultant 171",
    "positionUrl": "https://example.com/job/171",
    "location": "Japan",
    "seniority": "Mid",
    "uniqueKey": "Acme Financial 1-Japan-Director Consultant 171-Mid-https://example.com/job/171"
  },
  {
    "businessName": "Acme Financial 2",
    "positionName": "Director Consultant 172",
    "positionUrl": "https://example.com/job/172",
    "location": "Germany",
    "seniority": "Senior",
    "uniqueKey": "Acme Financial 2-Germany-Director Consultant 172-Senior-https://example.com/job/172"
  },
  {
    "businessName": "Acme Financial 3",
    "positionName": "Director Consultant 173",
    "positionUrl": "https://example.com/job/173",
    "location": "Brazil",
    "seniority": "Lead",
    "uniqueKey": "Acme Financial 3-Brazil-Director Consultant 173-Lead-https://example.com/job/173"
  },
  {
    "businessName": "Acme Financial 4",
    "positionName": "Director Consultant 174",
    "positionUrl": "https://example.com/job/174",
    "location": "India",
    "seniority": "VP",
    "uniqueKey": "Acme Financial 4-India-Director Consultant 174-VP-https://example.com/job/174"
  },
  {
    "businessName": "Acme Financial 5",
    "positionName": "Director Consultant 175",
    "positionUrl": "https://example.com/job/175",
    "location": "USA",
    "seniority": "Junior",
    "uniqueKey": "Acme Financial 5-USA-Director Consultant 175-Junior-https://example.com/job/175"
  },
  {
    "businessName": "Acme Financial 6",
    "positionName": "Director Consultant 176",
    "positionUrl": "https://example.com/job/176",
    "location": "Japan",
    "seniority": "Mid",
    "uniqueKey": "Acme Financial 6-Japan-Director Consultant 176-Mid-https://example.com/job/176"
  },
  {
    "businessName": "Acme Financial 7",
    "positionName": "Director Consultant 177",
    "positionUrl": "https://example.com/job/177",
    "location": "Germany",
    "seniority": "Senior",
    "uniqueKey": "Acme Financial 7-Germany-Director Consultant 177-Senior-https://example.com/job/177"
  },
  {
    "businessName": "Acme Financial 8",
    "positionName": "Director Consultant 178",
    "positionUrl": "https://example.com/job/178",
    "location": "Brazil",
    "seniority": "Lead",
    "uniqueKey": "Acme Financial 8-Brazil-Director Consultant 178-Lead-https://example.com/job/178"
  },
  {
    "businessName": "Acme Financial 9",
    "positionName": "Director Consultant 179",
    "positionUrl": "https://example.com/job/179",
    "location": "India",
    "seniority": "VP",
    "uniqueKey": "Acme Financial 9-India-Director Consultant 179-VP-https://example.com/job/179"
  },
  {
    "businessName": "Acme Financial 0",
    "positionName": "Director Consultant 180",
    "positionUrl": "https://example.com/job/180",
    "location": "USA",
    "seniority": "Junior",
    "uniqueKey": "Acme Financial 0-USA-Director Consultant 180-Junior-https://example.com/job/180"
  },
  {
    "businessName": "Acme Financial 1",
    "positionName": "Director Consultant 181",
    "positionUrl": "https://example.com/job/181",
    "location": "Japan",
    "seniority": "Mid",
    "uniqueKey": "Acme Financial 1-Japan-Director Consultant 181-Mid-https://example.com/job/181"
  },
  {
    "businessName": "Acme Financial 2",
    "positionName": "Director Consultant 182",
    "positionUrl": "https://example.com/job/182",
    "location": "Germany",
    "seniority": "Senior",
    "uniqueKey": "Acme Financial 2-Germany-Director Consultant 182-Senior-https://example.com/job/182"
  },
  {
    "businessName": "Acme Financial 3",
    "positionName": "Director Consultant 183",
    "positionUrl": "https://example.com/job/183",
    "location": "Brazil",
    "seniority": "Lead",
    "uniqueKey": "Acme Financial 3-Brazil-Director Consultant 183-Lead-https://example.com/job/183"
  },
  {
    "businessName": "Acme Financial 4",
    "positionName": "Director Consultant 184",
    "positionUrl": "https://example.com/job/184",
    "location": "India",
    "seniority": "VP",
    "uniqueKey": "Acme Financial 4-India-Director Consultant 184-VP-https://example.com/job/184"
  },
  {
    "businessName": "Acme Financial 5",
    "positionName": "Director Consultant 185",
    "positionUrl": "https://example.com/job/185",
    "location": "USA",
    "seniority": "Junior",
    "uniqueKey": "Acme Financial 5-USA-Director Consultant 185-Junior-https://example.com/job/185"
  },
  {
    "businessName": "Acme Financial 6",
    "positionName": "Director Consultant 186",
    "positionUrl": "https://example.com/job/186",
    "location": "Japan",
    "seniority": "Mid",
    "uniqueKey": "Acme Financial 6-Japan-Director Consultant 186-Mid-https://example.com/job/186"
  },
  {
    "businessName": "Acme Financial 7",
    "positionName": "Director Consultant 187",
    "positionUrl": "https://example.com/job/187",
    "location": "Germany",
    "seniority": "Senior",
    "uniqueKey": "Acme Financial 7-Germany-Director Consultant 187-Senior-https://example.com/job/187"
  },
  {
    "businessName": "Acme Financial 8",
    "positionName": "Director Consultant 188",
    "positionUrl": "https://example.com/job/188",
    "location": "Brazil",
    "seniority": "Lead",
    "uniqueKey": "Acme Financial 8-Brazil-Director Consultant 188-Lead-https://example.com/job/188"
  },
  {
    "businessName": "Acme Financial 9",
    "positionName": "Director Consultant 189",
    "positionUrl": "https://example.com/job/189",
    "location": "India",
    "seniority": "VP",
    "uniqueKey": "Acme Financial 9-India-Director Consultant 189-VP-https://example.com/job/189"
  },
  {
    "businessName": "Acme Financial 0",
    "positionName": "Director Consultant 190",
    "positionUrl": "https://example.com/job/190",
    "location": "USA",
    "seniority": "Junior",
    "uniqueKey": "Acme Financial 0-USA-Director Consultant 190-Junior-https://example.com/job/190"
  },
  {
    "businessName": "Acme Financial 1",
    "positionName": "Director Consultant 191",
    "positionUrl": "https://example.com/job/191",
    "location": "Japan",
    "seniority": "Mid",
    "uniqueKey": "Acme Financial 1-Japan-Director Consultant 191-Mid-https://example.com/job/191"
  },
  {
    "businessName": "Acme Financial 2",
    "positionName": "Director Consultant 192",
    "positionUrl": "https://example.com/job/192",
    "location": "Germany",
    "seniority": "Senior",
    "uniqueKey": "Acme Financial 2-Germany-Director Consultant 192-Senior-https://example.com/job/192"
  },
  {
    "businessName": "Acme Financial 3",
    "positionName": "Director Consultant 193",
    "positionUrl": "https://example.com/job/193",
    "location": "Brazil",
    "seniority": "Lead",
    "uniqueKey": "Acme Financial 3-Brazil-Director Consultant 193-Lead-https://example.com/job/193"
  },
  {
    "businessName": "Acme Financial 4",
    "positionName": "Director Consultant 194",
    "positionUrl": "https://example.com/job/194",
    "location": "India",
    "seniority": "VP",
    "uniqueKey": "Acme Financial 4-India-Director Consultant 194-VP-https://example.com/job/194"
  },
  {
    "businessName": "Acme Financial 5",
    "positionName": "Director Consultant 195",
    "positionUrl": "https://example.com/job/195",
    "location": "USA",
    "seniority": "Junior",
    "uniqueKey": "Acme Financial 5-USA-Director Consultant 195-Junior-https://example.com/job/195"
  },
  {
    "businessName": "Acme Financial 6",
    "positionName": "Director Consultant 196",
    "positionUrl": "https://example.com/job/196",
    "location": "Japan",
    "seniority": "Mid",
    "uniqueKey": "Acme Financial 6-Japan-Director Consultant 196-Mid-https://example.com/job/196"
  },
  {
    "businessName": "Acme Financial 7",
    "positionName": "Director Consultant 197",
    "positionUrl": "https://example.com/job/197",
    "location": "Germany",
    "seniority": "Senior",
    "uniqueKey": "Acme Financial 7-Germany-Director Consultant 197-Senior-https://example.com/job/197"
  },
  {
    "businessName": "Acme Financial 8",
    "positionName": "Director Consultant 198",
    "positionUrl": "https://example.com/job/198",
    "location": "Brazil",
    "seniority": "Lead",
    "uniqueKey": "Acme Financial 8-Brazil-Director Consultant 198-Lead-https://example.com/job/198"
  },
  {
    "businessName": "Acme Financial 9",
    "positionName": "Director Consultant 199",
    "positionUrl": "https://example.com/job/199",
    "location": "India",
    "seniority": "VP",
    "uniqueKey": "Acme Financial 9-India-Director Consultant 199-VP-https://example.com/job/199"
  },
  {
    "businessName": "Acme Financial 0",
    "positionName": "Director Consultant 200",
    "positionUrl": "https://example.com/job/200",
    "location": "USA",
    "seniority": "Junior",
    "uniqueKey": "Acme Financial 0-USA-Director Consultant 200-Junior-https://example.com/job/200"
  },
  {
    "businessName": "Acme Financial 1",
    "positionName": "Director Consultant 201",
    "positionUrl": "https://example.com/job/201",
    "location": "Japan",
    "seniority": "Mid",
    "uniqueKey": "Acme Financial 1-Japan-Director Consultant 201-Mid-https://example.com/job/201"
  },
  {
    "businessName": "Acme Financial 2",
    "positionName": "Director Consultant 202",
    "positionUrl": "https://example.com/job/202",
    "location": "Germany",
    "seniority": "Senior",
    "uniqueKey": "Acme Financial 2-Germany-Director Consultant 202-Senior-https://example.com/job/202"
  },
  {
    "businessName": "Acme Financial 3",
    "positionName": "Director Consultant 203",
    "positionUrl": "https://example.com/job/203",
    "location": "Brazil",
    "seniority": "Lead",
    "uniqueKey": "Acme Financial 3-Brazil-Director Consultant 203-Lead-https://example.com/job/203"
  },
  {
    "businessName": "Acme Financial 4",
    "positionName": "Director Consultant 204",
    "positionUrl": "https://example.com/job/204",
    "location": "India",
    "seniority": "VP",
    "uniqueKey": "Acme Financial 4-India-Director Consultant 204-VP-https://example.com/job/204"
  },
  {
    "businessName": "Acme Financial 5",
    "positionName": "Director Consultant 205",
    "positionUrl": "https://example.com/job/205",
    "location": "USA",
    "seniority": "Junior",
    "uniqueKey": "Acme Financial 5-USA-Director Consultant 205-Junior-https://example.com/job/205"
  },
  {
    "businessName": "Acme Financial 6",
    "positionName": "Director Consultant 206",
    "positionUrl": "https://example.com/job/206",
    "location": "Japan",
    "seniority": "Mid",
    "uniqueKey": "Acme Financial 6-Japan-Director Consultant 206-Mid-https://example.com/job/206"
  },
  {
    "businessName": "Acme Financial 7",
    "positionName": "Director Consultant 207",
    "positionUrl": "https://example.com/job/207",
    "location": "Germany",
    "seniority": "Senior",
    "uniqueKey": "Acme Financial 7-Germany-Director Consultant 207-Senior-https://example.com/job/207"
  },
  {
    "businessName": "Acme Financial 8",
    "positionName": "Director Consultant 208",
    "positionUrl": "https://example.com/job/208",
    "location": "Brazil",
    "seniority": "Lead",
    "uniqueKey": "Acme Financial 8-Brazil-Director Consultant 208-Lead-https://example.com/job/208"
  },
  {
    "businessName": "Acme Financial 9",
    "positionName": "Director Consultant 209",
    "positionUrl": "https://example.com/job/209",
    "location": "India",
    "seniority": "VP",
    "uniqueKey": "Acme Financial 9-India-Director Consultant 209-VP-https://example.com/job/209"
  },
  {
    "businessName": "Acme Financial 0",
    "positionName": "Director Consultant 210",
    "positionUrl": "https://example.com/job/210",
    "location": "USA",
    "seniority": "Junior",
    "uniqueKey": "Acme Financial 0-USA-Director Consultant 210-Junior-https://example.com/job/210"
  },
  {
    "businessName": "Acme Financial 1",
    "positionName": "Director Consultant 211",
    "positionUrl": "https://example.com/job/211",
    "location": "Japan",
    "seniority": "Mid",
    "uniqueKey": "Acme Financial 1-Japan-Director Consultant 211-Mid-https://example.com/job/211"
  },
  {
    "businessName": "Acme Financial 2",
    "positionName": "Director Consultant 212",
    "positionUrl": "https://example.com/job/212",
    "location": "Germany",
    "seniority": "Senior",
    "uniqueKey": "Acme Financial 2-Germany-Director Consultant 212-Senior-https://example.com/job/212"
  },
  {
    "businessName": "Acme Financial 3",
    "positionName": "Director Consultant 213",
    "positionUrl": "https://example.com/job/213",
    "location": "Brazil",
    "seniority": "Lead",
    "uniqueKey": "Acme Financial 3-Brazil-Director Consultant 213-Lead-https://example.com/job/213"
  },
  {
    "businessName": "Acme Financial 4",
    "positionName": "Director Consultant 214",
    "positionUrl": "https://example.com/job/214",
    "location": "India",
    "seniority": "VP",
    "uniqueKey": "Acme Financial 4-India-Director Consultant 214-VP-https://example.com/job/214"
  },
  {
    "businessName": "Acme Financial 5",
    "positionName": "Director Consultant 215",
    "positionUrl": "https://example.com/job/215",
    "location": "USA",
    "seniority": "Junior",
    "uniqueKey": "Acme Financial 5-USA-Director Consultant 215-Junior-https://example.com/job/215"
  },
  {
    "businessName": "Acme Financial 6",
    "positionName": "Director Consultant 216",
    "positionUrl": "https://example.com/job/216",
    "location": "Japan",
    "seniority": "Mid",
    "uniqueKey": "Acme Financial 6-Japan-Director Consultant 216-Mid-https://example.com/job/216"
  },
  {
    "businessName": "Acme Financial 7",
    "positionName": "Director Consultant 217",
    "positionUrl": "https://example.com/job/217",
    "location": "Germany",
    "seniority": "Senior",
    "uniqueKey": "Acme Financial 7-Germany-Director Consultant 217-Senior-https://example.com/job/217"
  },
  {
    "businessName": "Acme Financial 8",
    "positionName": "Director Consultant 218",
    "positionUrl": "https://example.com/job/218",
    "location": "Brazil",
    "seniority": "Lead",
    "uniqueKey": "Acme Financial 8-Brazil-Director Consultant 218-Lead-https://example.com/job/218"
  },
  {
    "businessName": "Acme Financial 9",
    "positionName": "Director Consultant 219",
    "positionUrl": "https://example.com/job/219",
    "location": "India",
    "seniority": "VP",
    "uniqueKey": "Acme Financial 9-India-Director Consultant 219-VP-https://example.com/job/219"
  },
  {
    "businessName": "Acme Financial 0",
    "positionName": "Director Consultant 220",
    "positionUrl": "https://example.com/job/220",
    "location": "USA",
    "seniority": "Junior",
    "uniqueKey": "Acme Financial 0-USA-Director Consultant 220-Junior-https://example.com/job/220"
  },
  {
    "businessName": "Acme Financial 1",
    "positionName": "Director Consultant 221",
    "positionUrl": "https://example.com/job/221",
    "location": "Japan",
    "seniority": "Mid",
    "uniqueKey": "Acme Financial 1-Japan-Director Consultant 221-Mid-https://example.com/job/221"
  },
  {
    "businessName": "Acme Financial 2",
    "positionName": "Director Consultant 222",
    "positionUrl": "https://example.com/job/222",
    "location": "Germany",
    "seniority": "Senior",
    "uniqueKey": "Acme Financial 2-Germany-Director Consultant 222-Senior-https://example.com/job/222"
  },
  {
    "businessName": "Acme Financial 3",
    "positionName": "Director Consultant 223",
    "positionUrl": "https://example.com/job/223",
    "location": "Brazil",
    "seniority": "Lead",
    "uniqueKey": "Acme Financial 3-Brazil-Director Consultant 223-Lead-https://example.com/job/223"
  },
  {
    "businessName": "Acme Financial 4",
    "positionName": "Director Consultant 224",
    "positionUrl": "https://example.com/job/224",
    "location": "India",
    "seniority": "VP",
    "uniqueKey": "Acme Financial 4-India-Director Consultant 224-VP-https://example.com/job/224"
  },
  {
    "businessName": "Acme Financial 5",
    "positionName": "Director Consultant 225",
    "positionUrl": "https://example.com/job/225",
    "location": "USA",
    "seniority": "Junior",
    "uniqueKey": "Acme Financial 5-USA-Director Consultant 225-Junior-https://example.com/job/225"
  },
  {
    "businessName": "Acme Financial 6",
    "positionName": "Director Consultant 226",
    "positionUrl": "https://example.com/job/226",
    "location": "Japan",
    "seniority": "Mid",
    "uniqueKey": "Acme Financial 6-Japan-Director Consultant 226-Mid-https://example.com/job/226"
  },
  {
    "businessName": "Acme Financial 7",
    "positionName": "Director Consultant 227",
    "positionUrl": "https://example.com/job/227",
    "location": "Germany",
    "seniority": "Senior",
    "uniqueKey": "Acme Financial 7-Germany-Director Consultant 227-Senior-https://example.com/job/227"
  },
  {
    "businessName": "Acme Financial 8",
    "positionName": "Director Consultant 228",
    "positionUrl": "https://example.com/job/228",
    "location": "Brazil",
    "seniority": "Lead",
    "uniqueKey": "Acme Financial 8-Brazil-Director Consultant 228-Lead-https://example.com/job/228"
  },
  {
    "businessName": "Acme Financial 9",
    "positionName": "Director Consultant 229",
    "positionUrl": "https://example.com/job/229",
    "location": "India",
    "seniority": "VP",
    "uniqueKey": "Acme Financial 9-India-Director Consultant 229-VP-https://example.com/job/229"
  },
  {
    "businessName": "Acme Financial 0",
    "positionName": "Director Consultant 230",
    "positionUrl": "https://example.com/job/230",
    "location": "USA",
    "seniority": "Junior",
    "uniqueKey": "Acme Financial 0-USA-Director Consultant 230-Junior-https://example.com/job/230"
  },
  {
    "businessName": "Acme Financial 1",
    "positionName": "Director Consultant 231",
    "positionUrl": "https://example.com/job/231",
    "location": "Japan",
    "seniority": "Mid",
    "uniqueKey": "Acme Financial 1-Japan-Director Consultant 231-Mid-https://example.com/job/231"
  },
  {
    "businessName": "Acme Financial 2",
    "positionName": "Director Consultant 232",
    "positionUrl": "https://example.com/job/232",
    "location": "Germany",
    "seniority": "Senior",
    "uniqueKey": "Acme Financial 2-Germany-Director Consultant 232-Senior-https://example.com/job/232"
  },
  {
    "businessName": "Acme Financial 3",
    "positionName": "Director Consultant 233",
    "positionUrl": "https://example.com/job/233",
    "location": "Brazil",
    "seniority": "Lead",
    "uniqueKey": "Acme Financial 3-Brazil-Director Consultant 233-Lead-https://example.com/job/233"
  },
  {
    "businessName": "Acme Financial 4",
    "positionName": "Director Consultant 234",
    "positionUrl": "https://example.com/job/234",
    "location": "India",
    "seniority": "VP",
    "uniqueKey": "Acme Financial 4-India-Director Consultant 234-VP-https://example.com/job/234"
  },
  {
    "businessName": "Acme Financial 5",
    "positionName": "Director Consultant 235",
    "positionUrl": "https://example.com/job/235",
    "location": "USA",
    "seniority": "Junior",
    "uniqueKey": "Acme Financial 5-USA-Director Consultant 235-Junior-https://example.com/job/235"
  },
  {
    "businessName": "Acme Financial 6",
    "positionName": "Director Consultant 236",
    "positionUrl": "https://example.com/job/236",
    "location": "Japan",
    "seniority": "Mid",
    "uniqueKey": "Acme Financial 6-Japan-Director Consultant 236-Mid-https://example.com/job/236"
  },
  {
    "businessName": "Acme Financial 7",
    "positionName": "Director Consultant 237",
    "positionUrl": "https://example.com/job/237",
    "location": "Germany",
    "seniority": "Senior",
    "uniqueKey": "Acme Financial 7-Germany-Director Consultant 237-Senior-https://example.com/job/237"
  },
  {
    "businessName": "Acme Financial 8",
    "positionName": "Director Consultant 238",
    "positionUrl": "https://example.com/job/238",
    "location": "Brazil",
    "seniority": "Lead",
    "uniqueKey": "Acme Financial 8-Brazil-Director Consultant 238-Lead-https://example.com/job/238"
  },
  {
    "businessName": "Acme Financial 9",
    "positionName": "Director Consultant 239",
    "positionUrl": "https://example.com/job/239",
    "location": "India",
    "seniority": "VP",
    "uniqueKey": "Acme Financial 9-India-Director Consultant 239-VP-https://example.com/job/239"
  },
  {
    "businessName": "Acme Financial 0",
    "positionName": "Director Consultant 240",
    "positionUrl": "https://example.com/job/240",
    "location": "USA",
    "seniority": "Junior",
    "uniqueKey": "Acme Financial 0-USA-Director Consultant 240-Junior-https://example.com/job/240"
  },
  {
    "businessName": "Acme Financial 1",
    "positionName": "Director Consultant 241",
    "positionUrl": "https://example.com/job/241",
    "location": "Japan",
    "seniority": "Mid",
    "uniqueKey": "Acme Financial 1-Japan-Director Consultant 241-Mid-https://example.com/job/241"
  },
  {
    "businessName": "Acme Financial 2",
    "positionName": "Director Consultant 242",
    "positionUrl": "https://example.com/job/242",
    "location": "Germany",
    "seniority": "Senior",
    "uniqueKey": "Acme Financial 2-Germany-Director Consultant 242-Senior-https://example.com/job/242"
  },
  {
    "businessName": "Acme Financial 3",
    "positionName": "Director Consultant 243",
    "positionUrl": "https://example.com/job/243",
    "location": "Brazil",
    "seniority": "Lead",
    "uniqueKey": "Acme Financial 3-Brazil-Director Consultant 243-Lead-https://example.com/job/243"
  },
  {
    "businessName": "Acme Financial 4",
    "positionName": "Director Consultant 244",
    "positionUrl": "https://example.com/job/244",
    "location": "India",
    "seniority": "VP",
    "uniqueKey": "Acme Financial 4-India-Director Consultant 244-VP-https://example.com/job/244"
  },
  {
    "businessName": "Acme Financial 5",
    "positionName": "Director Consultant 245",
    "positionUrl": "https://example.com/job/245",
    "location": "USA",
    "seniority": "Junior",
    "uniqueKey": "Acme Financial 5-USA-Director Consultant 245-Junior-https://example.com/job/245"
  },
  {
    "businessName": "Acme Financial 6",
    "positionName": "Director Consultant 246",
    "positionUrl": "https://example.com/job/246",
    "location": "Japan",
    "seniority": "Mid",
    "uniqueKey": "Acme Financial 6-Japan-Director Consultant 246-Mid-https://example.com/job/246"
  },
  {
    "businessName": "Acme Financial 7",
    "positionName": "Director Consultant 247",
    "positionUrl": "https://example.com/job/247",
    "location": "Germany",
    "seniority": "Senior",
    "uniqueKey": "Acme Financial 7-Germany-Director Consultant 247-Senior-https://example.com/job/247"
  },
  {
    "businessName": "Acme Financial 8",
    "positionName": "Director Consultant 248",
    "positionUrl": "https://example.com/job/248",
    "location": "Brazil",
    "seniority": "Lead",
    "uniqueKey": "Acme Financial 8-Brazil-Director Consultant 248-Lead-https://example.com/job/248"
  },
  {
    "businessName": "Acme Financial 9",
    "positionName": "Director Consultant 249",
    "positionUrl": "https://example.com/job/249",
    "location": "India",
    "seniority": "VP",
    "uniqueKey": "Acme Financial 9-India-Director Consultant 249-VP-https://example.com/job/249"
  },
  {
    "businessName": "Acme Financial 0",
    "positionName": "Director Consultant 250",
    "positionUrl": "https://example.com/job/250",
    "location": "USA",
    "seniority": "Junior",
    "uniqueKey": "Acme Financial 0-USA-Director Consultant 250-Junior-https://example.com/job/250"
  },
  {
    "businessName": "Acme Financial 1",
    "positionName": "Director Consultant 251",
    "positionUrl": "https://example.com/job/251",
    "location": "Japan",
    "seniority": "Mid",
    "uniqueKey": "Acme Financial 1-Japan-Director Consultant 251-Mid-https://example.com/job/251"
  },
  {
    "businessName": "Acme Financial 2",
    "positionName": "Director Consultant 252",
    "positionUrl": "https://example.com/job/252",
    "location": "Germany",
    "seniority": "Senior",
    "uniqueKey": "Acme Financial 2-Germany-Director Consultant 252-Senior-https://example.com/job/252"
  },
  {
    "businessName": "Acme Financial 3",
    "positionName": "Director Consultant 253",
    "positionUrl": "https://example.com/job/253",
    "location": "Brazil",
    "seniority": "Lead",
    "uniqueKey": "Acme Financial 3-Brazil-Director Consultant 253-Lead-https://example.com/job/253"
  },
  {
    "businessName": "Acme Financial 4",
    "positionName": "Director Consultant 254",
    "positionUrl": "https://example.com/job/254",
    "location": "India",
    "seniority": "VP",
    "uniqueKey": "Acme Financial 4-India-Director Consultant 254-VP-https://example.com/job/254"
  },
  {
    "businessName": "Acme Financial 5",
    "positionName": "Director Consultant 255",
    "positionUrl": "https://example.com/job/255",
    "location": "USA",
    "seniority": "Junior",
    "uniqueKey": "Acme Financial 5-USA-Director Consultant 255-Junior-https://example.com/job/255"
  },
  {
    "businessName": "Acme Financial 6",
    "positionName": "Director Consultant 256",
    "positionUrl": "https://example.com/job/256",
    "location": "Japan",
    "seniority": "Mid",
    "uniqueKey": "Acme Financial 6-Japan-Director Consultant 256-Mid-https://example.com/job/256"
  },
  {
    "businessName": "Acme Financial 7",
    "positionName": "Director Consultant 257",
    "positionUrl": "https://example.com/job/257",
    "location": "Germany",
    "seniority": "Senior",
    "uniqueKey": "Acme Financial 7-Germany-Director Consultant 257-Senior-https://example.com/job/257"
  },
  {
    "businessName": "Acme Financial 8",
    "positionName": "Director Consultant 258",
    "positionUrl": "https://example.com/job/258",
    "location": "Brazil",
    "seniority": "Lead",
    "uniqueKey": "Acme Financial 8-Brazil-Director Consultant 258-Lead-https://example.com/job/258"
  },
  {
    "businessName": "Acme Financial 9",
    "positionName": "Director Consultant 259",
    "positionUrl": "https://example.com/job/259",
    "location": "India",
    "seniority": "VP",
    "uniqueKey": "Acme Financial 9-India-Director Consultant 259-VP-https://example.com/job/259"
  },
  {
    "businessName": "Acme Financial 0",
    "positionName": "Director Consultant 260",
    "positionUrl": "https://example.com/job/260",
    "location": "USA",
    "seniority": "Junior",
    "uniqueKey": "Acme Financial 0-USA-Director Consultant 260-Junior-https://example.com/job/260"
  },
  {
    "businessName": "Acme Financial 1",
    "positionName": "Director Consultant 261",
    "positionUrl": "https://example.com/job/261",
    "location": "Japan",
    "seniority": "Mid",
    "uniqueKey": "Acme Financial 1-Japan-Director Consultant 261-Mid-https://example.com/job/261"
  },
  {
    "businessName": "Acme Financial 2",
    "positionName": "Director Consultant 262",
    "positionUrl": "https://example.com/job/262",
    "location": "Germany",
    "seniority": "Senior",
    "uniqueKey": "Acme Financial 2-Germany-Director Consultant 262-Senior-https://example.com/job/262"
  },
  {
    "businessName": "Acme Financial 3",
    "positionName": "Director Consultant 263",
    "positionUrl": "https://example.com/job/263",
    "location": "Brazil",
    "seniority": "Lead",
    "uniqueKey": "Acme Financial 3-Brazil-Director Consultant 263-Lead-https://example.com/job/263"
  },
  {
    "businessName": "Acme Financial 4",
    "positionName": "Director Consultant 264",
    "positionUrl": "https://example.com/job/264",
    "location": "India",
    "seniority": "VP",
    "uniqueKey": "Acme Financial 4-India-Director Consultant 264-VP-https://example.com/job/264"
  },
  {
    "businessName": "Acme Financial 5",
    "positionName": "Director Consultant 265",
    "positionUrl": "https://example.com/job/265",
    "location": "USA",
    "seniority": "Junior",
    "uniqueKey": "Acme Financial 5-USA-Director Consultant 265-Junior-https://example.com/job/265"
  },
  {
    "businessName": "Acme Financial 6",
    "positionName": "Director Consultant 266",
    "positionUrl": "https://example.com/job/266",
    "location": "Japan",
    "seniority": "Mid",
    "uniqueKey": "Acme Financial 6-Japan-Director Consultant 266-Mid-https://example.com/job/266"
  },
  {
    "businessName": "Acme Financial 7",
    "positionName": "Director Consultant 267",
    "positionUrl": "https://example.com/job/267",
    "location": "Germany",
    "seniority": "Senior",
    "uniqueKey": "Acme Financial 7-Germany-Director Consultant 267-Senior-https://example.com/job/267"
  },
  {
    "businessName": "Acme Financial 8",
    "positionName": "Director Consultant 268",
    "positionUrl": "https://example.com/job/268",
    "location": "Brazil",
    "seniority": "Lead",
    "uniqueKey": "Acme Financial 8-Brazil-Director Consultant 268-Lead-https://example.com/job/268"
  },
  {
    "businessName": "Acme Financial 9",
    "positionName": "Director Consultant 269",
    "positionUrl": "https://example.com/job/269",
    "location": "India",
    "seniority": "VP",
    "uniqueKey": "Acme Financial 9-India-Director Consultant 269-VP-https://example.com/job/269"
  },
  {
    "businessName": "Acme Financial 0",
    "positionName": "Director Consultant 270",
    "positionUrl": "https://example.com/job/270",
    "location": "USA",
    "seniority": "Junior",
    "uniqueKey": "Acme Financial 0-USA-Director Consultant 270-Junior-https://example.com/job/270"
  },
  {
    "businessName": "Acme Financial 1",
    "positionName": "Director Consultant 271",
    "positionUrl": "https://example.com/job/271",
    "location": "Japan",
    "seniority": "Mid",
    "uniqueKey": "Acme Financial 1-Japan-Director Consultant 271-Mid-https://example.com/job/271"
  },
  {
    "businessName": "Acme Financial 2",
    "positionName": "Director Consultant 272",
    "positionUrl": "https://example.com/job/272",
    "location": "Germany",
    "seniority": "Senior",
    "uniqueKey": "Acme Financial 2-Germany-Director Consultant 272-Senior-https://example.com/job/272"
  },
  {
    "businessName": "Acme Financial 3",
    "positionName": "Director Consultant 273",
    "positionUrl": "https://example.com/job/273",
    "location": "Brazil",
    "seniority": "Lead",
    "uniqueKey": "Acme Financial 3-Brazil-Director Consultant 273-Lead-https://example.com/job/273"
  },
  {
    "businessName": "Acme Financial 4",
    "positionName": "Director Consultant 274",
    "positionUrl": "https://example.com/job/274",
    "location": "India",
    "seniority": "VP",
    "uniqueKey": "Acme Financial 4-India-Director Consultant 274-VP-https://example.com/job/274"
  },
  {
    "businessName": "Acme Financial 5",
    "positionName": "Director Consultant 275",
    "positionUrl": "https://example.com/job/275",
    "location": "USA",
    "seniority": "Junior",
    "uniqueKey": "Acme Financial 5-USA-Director Consultant 275-Junior-https://example.com/job/275"
  },
  {
    "businessName": "Acme Financial 6",
    "positionName": "Director Consultant 276",
    "positionUrl": "https://example.com/job/276",
    "location": "Japan",
    "seniority": "Mid",
    "uniqueKey": "Acme Financial 6-Japan-Director Consultant 276-Mid-https://example.com/job/276"
  },
  {
    "businessName": "Acme Financial 7",
    "positionName": "Director Consultant 277",
    "positionUrl": "https://example.com/job/277",
    "location": "Germany",
    "seniority": "Senior",
    "uniqueKey": "Acme Financial 7-Germany-Director Consultant 277-Senior-https://example.com/job/277"
  },
  {
    "businessName": "Acme Financial 8",
    "positionName": "Director Consultant 278",
    "positionUrl": "https://example.com/job/278",
    "location": "Brazil",
    "seniority": "Lead",
    "uniqueKey": "Acme Financial 8-Brazil-Director Consultant 278-Lead-https://example.com/job/278"
  },
  {
    "businessName": "Acme Financial 9",
    "positionName": "Director Consultant 279",
    "positionUrl": "https://example.com/job/279",
    "location": "India",
    "seniority": "VP",
    "uniqueKey": "Acme Financial 9-India-Director Consultant 279-VP-https://example.com/job/279"
  },
  {
    "businessName": "Acme Financial 0",
    "positionName": "Director Consultant 280",
    "positionUrl": "https://example.com/job/280",
    "location": "USA",
    "seniority": "Junior",
    "uniqueKey": "Acme Financial 0-USA-Director Consultant 280-Junior-https://example.com/job/280"
  },
  {
    "businessName": "Acme Financial 1",
    "positionName": "Director Consultant 281",
    "positionUrl": "https://example.com/job/281",
    "location": "Japan",
    "seniority": "Mid",
    "uniqueKey": "Acme Financial 1-Japan-Director Consultant 281-Mid-https://example.com/job/281"
  },
  {
    "businessName": "Acme Financial 2",
    "positionName": "Director Consultant 282",
    "positionUrl": "https://example.com/job/282",
    "location": "Germany",
    "seniority": "Senior",
    "uniqueKey": "Acme Financial 2-Germany-Director Consultant 282-Senior-https://example.com/job/282"
  },
  {
    "businessName": "Acme Financial 3",
    "positionName": "Director Consultant 283",
    "positionUrl": "https://example.com/job/283",
    "location": "Brazil",
    "seniority": "Lead",
    "uniqueKey": "Acme Financial 3-Brazil-Director Consultant 283-Lead-https://example.com/job/283"
  },
  {
    "businessName": "Acme Financial 4",
    "positionName": "Director Consultant 284",
    "positionUrl": "https://example.com/job/284",
    "location": "India",
    "seniority": "VP",
    "uniqueKey": "Acme Financial 4-India-Director Consultant 284-VP-https://example.com/job/284"
  },
  {
    "businessName": "Acme Financial 5",
    "positionName": "Director Consultant 285",
    "positionUrl": "https://example.com/job/285",
    "location": "USA",
    "seniority": "Junior",
    "uniqueKey": "Acme Financial 5-USA-Director Consultant 285-Junior-https://example.com/job/285"
  },
  {
    "businessName": "Acme Financial 6",
    "positionName": "Director Consultant 286",
    "positionUrl": "https://example.com/job/286",
    "location": "Japan",
    "seniority": "Mid",
    "uniqueKey": "Acme Financial 6-Japan-Director Consultant 286-Mid-https://example.com/job/286"
  },
  {
    "businessName": "Acme Financial 7",
    "positionName": "Director Consultant 287",
    "positionUrl": "https://example.com/job/287",
    "location": "Germany",
    "seniority": "Senior",
    "uniqueKey": "Acme Financial 7-Germany-Director Consultant 287-Senior-https://example.com/job/287"
  },
  {
    "businessName": "Acme Financial 8",
    "positionName": "Director Consultant 288",
    "positionUrl": "https://example.com/job/288",
    "location": "Brazil",
    "seniority": "Lead",
    "uniqueKey": "Acme Financial 8-Brazil-Director Consultant 288-Lead-https://example.com/job/288"
  },
  {
    "businessName": "Acme Financial 9",
    "positionName": "Director Consultant 289",
    "positionUrl": "https://example.com/job/289",
    "location": "India",
    "seniority": "VP",
    "uniqueKey": "Acme Financial 9-India-Director Consultant 289-VP-https://example.com/job/289"
  },
  {
    "businessName": "Acme Financial 0",
    "positionName": "Director Consultant 290",
    "positionUrl": "https://example.com/job/290",
    "location": "USA",
    "seniority": "Junior",
    "uniqueKey": "Acme Financial 0-USA-Director Consultant 290-Junior-https://example.com/job/290"
  },
  {
    "businessName": "Acme Financial 1",
    "positionName": "Director Consultant 291",
    "positionUrl": "https://example.com/job/291",
    "location": "Japan",
    "seniority": "Mid",
    "uniqueKey": "Acme Financial 1-Japan-Director Consultant 291-Mid-https://example.com/job/291"
  },
  {
    "businessName": "Acme Financial 2",
    "positionName": "Director Consultant 292",
    "positionUrl": "https://example.com/job/292",
    "location": "Germany",
    "seniority": "Senior",
    "uniqueKey": "Acme Financial 2-Germany-Director Consultant 292-Senior-https://example.com/job/292"
  },
  {
    "businessName": "Acme Financial 3",
    "positionName": "Director Consultant 293",
    "positionUrl": "https://example.com/job/293",
    "location": "Brazil",
    "seniority": "Lead",
    "uniqueKey": "Acme Financial 3-Brazil-Director Consultant 293-Lead-https://example.com/job/293"
  },
  {
    "businessName": "Acme Financial 4",
    "positionName": "Director Consultant 294",
    "positionUrl": "https://example.com/job/294",
    "location": "India",
    "seniority": "VP",
    "uniqueKey": "Acme Financial 4-India-Director Consultant 294-VP-https://example.com/job/294"
  },
  {
    "businessName": "Acme Financial 5",
    "positionName": "Director Consultant 295",
    "positionUrl": "https://example.com/job/295",
    "location": "USA",
    "seniority": "Junior",
    "uniqueKey": "Acme Financial 5-USA-Director Consultant 295-Junior-https://example.com/job/295"
  },
  {
    "businessName": "Acme Financial 6",
    "positionName": "Director Consultant 296",
    "positionUrl": "https://example.com/job/296",
    "location": "Japan",
    "seniority": "Mid",
    "uniqueKey": "Acme Financial 6-Japan-Director Consultant 296-Mid-https://example.com/job/296"
  },
  {
    "businessName": "Acme Financial 7",
    "positionName": "Director Consultant 297",
    "positionUrl": "https://example.com/job/297",
    "location": "Germany",
    "seniority": "Senior",
    "uniqueKey": "Acme Financial 7-Germany-Director Consultant 297-Senior-https://example.com/job/297"
  },
  {
    "businessName": "Acme Financial 8",
    "positionName": "Director Consultant 298",
    "positionUrl": "https://example.com/job/298",
    "location": "Brazil",
    "seniority": "Lead",
    "uniqueKey": "Acme Financial 8-Brazil-Director Consultant 298-Lead-https://example.com/job/298"
  },
  {
    "businessName": "Acme Financial 9",
    "positionName": "Director Consultant 299",
    "positionUrl": "https://example.com/job/299",
    "location": "India",
    "seniority": "VP",
    "uniqueKey": "Acme Financial 9-India-Director Consultant 299-VP-https://example.com/job/299"
  }
]